cynric/__init__.py
cynric/exceptions.py
cynric/instantiation.py
cynric/py.typed
cynric/api/__init__.py
cynric/api/api_client.py
cynric/api/authentication.py
cynric/api/bc.py
cynric/api/endpoints.py
cynric/api/integrity.py
cynric/api/logger.py
cynric/api/queue.py
cynric/api/utilities.py
cynric/credentials/credentials.py
cynric/credentials/helpers.py
cynric/credentials/resolution.py
cynric/dataset_manager/__init__.py
cynric/dataset_manager/convenience.py
cynric/dataset_manager/mapper.py
cynric/dataset_manager/navigator.py
cynric/demo/__init__.py
cynric/demo/demo.py
cynric/forms/__init__.py
cynric/forms/convert.py
cynric/forms/create.py
cynric/support/__init__.py
cynric/support/version_check.py
cynric/uploading/__init__.py
cynric/uploading/convenience.py
cynric/uploading/helpers.py
cynric/uploading/uploading.py
cynric/validation/__init__.py
cynric/validation/validation.py
cynric-1.0.0.dist-info/METADATA
cynric-1.0.0.dist-info/WHEEL
cynric-1.0.0.dist-info/RECORD
