Metadata-Version: 2.4
Name: cynric
Version: 1.0.0
Summary: Cynric is a package for validating and uploading data to the Wessex SDE
Author: Ben Sale, Michael George, Cai Davis
License-Expression: CC-BY-NC-4.0
Requires-Python: <4,>=3.11
Requires-Dist: keyring>=25.7.0
Requires-Dist: keyrings-alt>=5.0.2; sys_platform == 'linux'
Requires-Dist: polars>=1.35.2
Requires-Dist: python-dotenv>=1.2.1
Requires-Dist: rapidfuzz>=3.14.3
Requires-Dist: urllib3>=2.5.0
Requires-Dist: valediction>=1.2.0
